clwdevops/__init__.py
clwdevops/aws.py
clwdevops/connect.py
clwdevops/csvutils.py
clwdevops/utils.py
clwdevops-0.4.5.dist-info/METADATA
clwdevops-0.4.5.dist-info/WHEEL
clwdevops-0.4.5.dist-info/top_level.txt
clwdevops-0.4.5.dist-info/RECORD
