Metadata-Version: 2.4
Name: clwdevops
Version: 0.4.5
Summary: Collection of utilities for Clairways devops and lambda functions
Author-email: Justice Amoh <justice@clairways.com>
License: COMMERCIAL
Project-URL: Source, https://github.com/clairways/clwdevops
Requires-Python: >=3.8
Requires-Dist: boto3
Requires-Dist: omegaconf
